[
  {
    "time": 0,
    "type": "sentence",
    "start": 7,
    "end": 136,
    "value": "As you'll see<break time=\"800ms\"/>our performance this quarter has been<break time=\"900ms\"/>challenging but ultimately promising."
  },
  {
    "time": 200,
    "type": "word",
    "start": 7,
    "end": 9,
    "value": "As"
  },
  {
    "time": 200,
    "type": "viseme",
    "value": "a"
  },
  {
    "time": 237,
    "type": "viseme",
    "value": "s"
  },
  {
    "time": 337,
    "type": "word",
    "start": 10,
    "end": 16,
    "value": "you'll"
  },
  {
    "time": 337,
    "type": "viseme",
    "value": "i"
  },
  {
    "time": 450,
    "type": "viseme",
    "value": "u"
  },
  {
    "time": 500,
    "type": "viseme",
    "value": "t"
  },
  {
    "time": 625,
    "type": "word",
    "start": 17,
    "end": 20,
    "value": "see"
  },
  {
    "time": 625,
    "type": "viseme",
    "value": "s"
  },
  {
    "time": 837,
    "type": "viseme",
    "value": "i"
  },
  {
    "time": 1137,
    "type": "viseme",
    "value": "sil"
  },
  {
    "time": 1193,
    "type": "word",
    "start": 20,
    "end": 41,
    "value": "<break time=\"800ms\"/>"
  },
  {
    "time": 2050,
    "type": "word",
    "start": 41,
    "end": 44,
    "value": "our"
  },
  {
    "time": 2050,
    "type": "viseme",
    "value": "a"
  },
  {
    "time": 2262,
    "type": "viseme",
    "value": "@"
  },
  {
    "time": 2387,
    "type": "word",
    "start": 45,
    "end": 56,
    "value": "performance"
  },
  {
    "time": 2387,
    "type": "viseme",
    "value": "p"
  },
  {
    "time": 2425,
    "type": "viseme",
    "value": "@"
  },
  {
    "time": 2550,
    "type": "viseme",
    "value": "f"
  },
  {
    "time": 2675,
    "type": "viseme",
    "value": "O"
  },
  {
    "time": 2737,
    "type": "viseme",
    "value": "p"
  },
  {
    "time": 2825,
    "type": "viseme",
    "value": "@"
  },
  {
    "time": 2887,
    "type": "viseme",
    "value": "t"
  },
  {
    "time": 2925,
    "type": "viseme",
    "value": "s"
  },
  {
    "time": 3112,
    "type": "word",
    "start": 57,
    "end": 61,
    "value": "this"
  },
  {
    "time": 3112,
    "type": "viseme",
    "value": "T"
  },
  {
    "time": 3125,
    "type": "viseme",
    "value": "i"
  },
  {
    "time": 3187,
    "type": "viseme",
    "value": "s"
  },
  {
    "time": 3262,
    "type": "word",
    "start": 62,
    "end": 69,
    "value": "quarter"
  },
  {
    "time": 3262,
    "type": "viseme",
    "value": "k"
  },
  {
    "time": 3362,
    "type": "viseme",
    "value": "u"
  },
  {
    "time": 3437,
    "type": "viseme",
    "value": "O"
  },
  {
    "time": 3550,
    "type": "viseme",
    "value": "t"
  },
  {
    "time": 3650,
    "type": "viseme",
    "value": "@"
  },
  {
    "time": 3750,
    "type": "word",
    "start": 70,
    "end": 73,
    "value": "has"
  },
  {
    "time": 3750,
    "type": "viseme",
    "value": "k"
  },
  {
    "time": 3800,
    "type": "viseme",
    "value": "a"
  },
  {
    "time": 3862,
    "type": "viseme",
    "value": "s"
  },
  {
    "time": 3925,
    "type": "word",
    "start": 74,
    "end": 78,
    "value": "been"
  },
  {
    "time": 3925,
    "type": "viseme",
    "value": "p"
  },
  {
    "time": 4012,
    "type": "viseme",
    "value": "i"
  },
  {
    "time": 4237,
    "type": "viseme",
    "value": "t"
  },
  {
    "time": 4387,
    "type": "viseme",
    "value": "sil"
  },
  {
    "time": 4456,
    "type": "word",
    "start": 78,
    "end": 99,
    "value": "<break time=\"900ms\"/>"
  },
  {
    "time": 5425,
    "type": "word",
    "start": 99,
    "end": 110,
    "value": "challenging"
  },
  {
    "time": 5425,
    "type": "viseme",
    "value": "S"
  },
  {
    "time": 5700,
    "type": "viseme",
    "value": "a"
  },
  {
    "time": 5762,
    "type": "viseme",
    "value": "t"
  },
  {
    "time": 5825,
    "type": "viseme",
    "value": "i"
  },
  {
    "time": 5887,
    "type": "viseme",
    "value": "t"
  },
  {
    "time": 5950,
    "type": "viseme",
    "value": "S"
  },
  {
    "time": 6012,
    "type": "viseme",
    "value": "i"
  },
  {
    "time": 6112,
    "type": "viseme",
    "value": "k"
  },
  {
    "time": 6200,
    "type": "word",
    "start": 111,
    "end": 114,
    "value": "but"
  },
  {
    "time": 6200,
    "type": "viseme",
    "value": "p"
  },
  {
    "time": 6250,
    "type": "viseme",
    "value": "@"
  },
  {
    "time": 6262,
    "type": "viseme",
    "value": "t"
  },
  {
    "time": 6387,
    "type": "word",
    "start": 115,
    "end": 125,
    "value": "ultimately"
  },
  {
    "time": 6387,
    "type": "viseme",
    "value": "E"
  },
  {
    "time": 6450,
    "type": "viseme",
    "value": "t"
  },
  {
    "time": 6512,
    "type": "viseme",
    "value": "t"
  },
  {
    "time": 6575,
    "type": "viseme",
    "value": "i"
  },
  {
    "time": 6637,
    "type": "viseme",
    "value": "p"
  },
  {
    "time": 6650,
    "type": "viseme",
    "value": "@"
  },
  {
    "time": 6775,
    "type": "viseme",
    "value": "t"
  },
  {
    "time": 6837,
    "type": "viseme",
    "value": "t"
  },
  {
    "time": 6862,
    "type": "viseme",
    "value": "i"
  },
  {
    "time": 6962,
    "type": "word",
    "start": 126,
    "end": 135,
    "value": "promising"
  },
  {
    "time": 6962,
    "type": "viseme",
    "value": "p"
  },
  {
    "time": 7012,
    "type": "viseme",
    "value": "r"
  },
  {
    "time": 7037,
    "type": "viseme",
    "value": "O"
  },
  {
    "time": 7100,
    "type": "viseme",
    "value": "p"
  },
  {
    "time": 7162,
    "type": "viseme",
    "value": "i"
  },
  {
    "time": 7325,
    "type": "viseme",
    "value": "s"
  },
  {
    "time": 7350,
    "type": "viseme",
    "value": "i"
  },
  {
    "time": 7450,
    "type": "viseme",
    "value": "k"
  },
  {
    "time": 7762,
    "type": "viseme",
    "value": "sil"
  }
]