[
  {
    "time": 0,
    "type": "sentence",
    "start": 28,
    "end": 43,
    "value": "Of course, sir!"
  },
  {
    "time": 12,
    "type": "word",
    "start": 28,
    "end": 30,
    "value": "Of"
  },
  {
    "time": 12,
    "type": "viseme",
    "value": "@"
  },
  {
    "time": 114,
    "type": "viseme",
    "value": "f"
  },
  {
    "time": 206,
    "type": "word",
    "start": 31,
    "end": 37,
    "value": "course"
  },
  {
    "time": 206,
    "type": "viseme",
    "value": "k"
  },
  {
    "time": 257,
    "type": "viseme",
    "value": "O"
  },
  {
    "time": 308,
    "type": "viseme",
    "value": "r"
  },
  {
    "time": 410,
    "type": "viseme",
    "value": "s"
  },
  {
    "time": 461,
    "type": "viseme",
    "value": "sil"
  },
  {
    "time": 649,
    "type": "word",
    "start": 39,
    "end": 42,
    "value": "sir"
  },
  {
    "time": 649,
    "type": "viseme",
    "value": "s"
  },
  {
    "time": 853,
    "type": "viseme",
    "value": "E"
  },
  {
    "time": 975,
    "type": "viseme",
    "value": "sil"
  },
  {
    "time": 1618,
    "type": "sentence",
    "start": 44,
    "end": 84,
    "value": "I've prepared a comprehensive dashboard."
  },
  {
    "time": 1630,
    "type": "word",
    "start": 44,
    "end": 48,
    "value": "I've"
  },
  {
    "time": 1630,
    "type": "viseme",
    "value": "a"
  },
  {
    "time": 1773,
    "type": "viseme",
    "value": "f"
  },
  {
    "time": 1865,
    "type": "word",
    "start": 49,
    "end": 57,
    "value": "prepared"
  },
  {
    "time": 1865,
    "type": "viseme",
    "value": "p"
  },
  {
    "time": 1875,
    "type": "viseme",
    "value": "r"
  },
  {
    "time": 1926,
    "type": "viseme",
    "value": "@"
  },
  {
    "time": 1988,
    "type": "viseme",
    "value": "p"
  },
  {
    "time": 2028,
    "type": "viseme",
    "value": "E"
  },
  {
    "time": 2080,
    "type": "viseme",
    "value": "r"
  },
  {
    "time": 2131,
    "type": "viseme",
    "value": "t"
  },
  {
    "time": 2335,
    "type": "word",
    "start": 58,
    "end": 59,
    "value": "a"
  },
  {
    "time": 2335,
    "type": "viseme",
    "value": "@"
  },
  {
    "time": 2437,
    "type": "word",
    "start": 60,
    "end": 73,
    "value": "comprehensive"
  },
  {
    "time": 2437,
    "type": "viseme",
    "value": "k"
  },
  {
    "time": 2467,
    "type": "viseme",
    "value": "a"
  },
  {
    "time": 2549,
    "type": "viseme",
    "value": "p"
  },
  {
    "time": 2559,
    "type": "viseme",
    "value": "p"
  },
  {
    "time": 2641,
    "type": "viseme",
    "value": "r"
  },
  {
    "time": 2692,
    "type": "viseme",
    "value": "i"
  },
  {
    "time": 2702,
    "type": "viseme",
    "value": "k"
  },
  {
    "time": 2743,
    "type": "viseme",
    "value": "E"
  },
  {
    "time": 2815,
    "type": "viseme",
    "value": "t"
  },
  {
    "time": 2896,
    "type": "viseme",
    "value": "s"
  },
  {
    "time": 2947,
    "type": "viseme",
    "value": "i"
  },
  {
    "time": 3019,
    "type": "viseme",
    "value": "f"
  },
  {
    "time": 3100,
    "type": "word",
    "start": 74,
    "end": 83,
    "value": "dashboard"
  },
  {
    "time": 3100,
    "type": "viseme",
    "value": "t"
  },
  {
    "time": 3151,
    "type": "viseme",
    "value": "a"
  },
  {
    "time": 3223,
    "type": "viseme",
    "value": "S"
  },
  {
    "time": 3356,
    "type": "viseme",
    "value": "p"
  },
  {
    "time": 3437,
    "type": "viseme",
    "value": "O"
  },
  {
    "time": 3478,
    "type": "viseme",
    "value": "r"
  },
  {
    "time": 3570,
    "type": "viseme",
    "value": "t"
  },
  {
    "time": 3662,
    "type": "viseme",
    "value": "sil"
  },
  {
    "time": 3799,
    "type": "word",
    "start": 85,
    "end": 106,
    "value": "<break time=\"300ms\"/>"
  },
  {
    "time": 4479,
    "type": "sentence",
    "start": 106,
    "end": 186,
    "value": "Just<break time=\"200ms\"/>one moment<break time=\"200ms\"/>while I share my screen."
  },
  {
    "time": 4492,
    "type": "word",
    "start": 106,
    "end": 110,
    "value": "Just"
  },
  {
    "time": 4492,
    "type": "viseme",
    "value": "S"
  },
  {
    "time": 4635,
    "type": "viseme",
    "value": "E"
  },
  {
    "time": 4676,
    "type": "viseme",
    "value": "s"
  },
  {
    "time": 4757,
    "type": "viseme",
    "value": "t"
  },
  {
    "time": 4890,
    "type": "viseme",
    "value": "sil"
  },
  {
    "time": 4952,
    "type": "word",
    "start": 110,
    "end": 131,
    "value": "<break time=\"200ms\"/>"
  },
  {
    "time": 5215,
    "type": "word",
    "start": 131,
    "end": 134,
    "value": "one"
  },
  {
    "time": 5215,
    "type": "viseme",
    "value": "u"
  },
  {
    "time": 5368,
    "type": "viseme",
    "value": "E"
  },
  {
    "time": 5470,
    "type": "viseme",
    "value": "t"
  },
  {
    "time": 5552,
    "type": "word",
    "start": 135,
    "end": 141,
    "value": "moment"
  },
  {
    "time": 5552,
    "type": "viseme",
    "value": "p"
  },
  {
    "time": 5572,
    "type": "viseme",
    "value": "o"
  },
  {
    "time": 5644,
    "type": "viseme",
    "value": "p"
  },
  {
    "time": 5725,
    "type": "viseme",
    "value": "@"
  },
  {
    "time": 5827,
    "type": "viseme",
    "value": "t"
  },
  {
    "time": 5878,
    "type": "viseme",
    "value": "t"
  },
  {
    "time": 5940,
    "type": "viseme",
    "value": "sil"
  },
  {
    "time": 5996,
    "type": "word",
    "start": 141,
    "end": 162,
    "value": "<break time=\"200ms\"/>"
  },
  {
    "time": 6252,
    "type": "word",
    "start": 162,
    "end": 167,
    "value": "while"
  },
  {
    "time": 6252,
    "type": "viseme",
    "value": "u"
  },
  {
    "time": 6375,
    "type": "viseme",
    "value": "a"
  },
  {
    "time": 6507,
    "type": "viseme",
    "value": "t"
  },
  {
    "time": 6661,
    "type": "word",
    "start": 168,
    "end": 169,
    "value": "I"
  },
  {
    "time": 6661,
    "type": "viseme",
    "value": "a"
  },
  {
    "time": 6773,
    "type": "word",
    "start": 170,
    "end": 175,
    "value": "share"
  },
  {
    "time": 6773,
    "type": "viseme",
    "value": "S"
  },
  {
    "time": 6783,
    "type": "viseme",
    "value": "E"
  },
  {
    "time": 6906,
    "type": "viseme",
    "value": "r"
  },
  {
    "time": 7008,
    "type": "word",
    "start": 176,
    "end": 178,
    "value": "my"
  },
  {
    "time": 7008,
    "type": "viseme",
    "value": "p"
  },
  {
    "time": 7079,
    "type": "viseme",
    "value": "a"
  },
  {
    "time": 7171,
    "type": "word",
    "start": 179,
    "end": 185,
    "value": "screen"
  },
  {
    "time": 7171,
    "type": "viseme",
    "value": "s"
  },
  {
    "time": 7232,
    "type": "viseme",
    "value": "k"
  },
  {
    "time": 7283,
    "type": "viseme",
    "value": "r"
  },
  {
    "time": 7334,
    "type": "viseme",
    "value": "i"
  },
  {
    "time": 7426,
    "type": "viseme",
    "value": "t"
  },
  {
    "time": 7477,
    "type": "viseme",
    "value": "sil"
  }
]