[
  {
    "time": 0,
    "type": "sentence",
    "start": 0,
    "end": 13,
    "value": "Hey everyone!"
  },
  {
    "time": 137,
    "type": "word",
    "start": 0,
    "end": 3,
    "value": "Hey"
  },
  {
    "time": 137,
    "type": "viseme",
    "value": "k"
  },
  {
    "time": 237,
    "type": "viseme",
    "value": "e"
  },
  {
    "time": 337,
    "type": "word",
    "start": 4,
    "end": 12,
    "value": "everyone"
  },
  {
    "time": 337,
    "type": "viseme",
    "value": "E"
  },
  {
    "time": 450,
    "type": "viseme",
    "value": "f"
  },
  {
    "time": 500,
    "type": "viseme",
    "value": "r"
  },
  {
    "time": 562,
    "type": "viseme",
    "value": "i"
  },
  {
    "time": 625,
    "type": "viseme",
    "value": "u"
  },
  {
    "time": 712,
    "type": "viseme",
    "value": "E"
  },
  {
    "time": 750,
    "type": "viseme",
    "value": "t"
  },
  {
    "time": 987,
    "type": "viseme",
    "value": "sil"
  },
  {
    "time": 1380,
    "type": "sentence",
    "start": 14,
    "end": 86,
    "value": "I've put together the Q4 highlights and a few slides on early Q1 trends."
  },
  {
    "time": 1517,
    "type": "word",
    "start": 14,
    "end": 18,
    "value": "I've"
  },
  {
    "time": 1517,
    "type": "viseme",
    "value": "a"
  },
  {
    "time": 1580,
    "type": "viseme",
    "value": "f"
  },
  {
    "time": 1680,
    "type": "word",
    "start": 19,
    "end": 22,
    "value": "put"
  },
  {
    "time": 1680,
    "type": "viseme",
    "value": "p"
  },
  {
    "time": 1755,
    "type": "viseme",
    "value": "u"
  },
  {
    "time": 1767,
    "type": "viseme",
    "value": "t"
  },
  {
    "time": 1880,
    "type": "word",
    "start": 23,
    "end": 31,
    "value": "together"
  },
  {
    "time": 1880,
    "type": "viseme",
    "value": "t"
  },
  {
    "time": 1942,
    "type": "viseme",
    "value": "@"
  },
  {
    "time": 2005,
    "type": "viseme",
    "value": "k"
  },
  {
    "time": 2017,
    "type": "viseme",
    "value": "E"
  },
  {
    "time": 2192,
    "type": "viseme",
    "value": "T"
  },
  {
    "time": 2205,
    "type": "viseme",
    "value": "E"
  },
  {
    "time": 2292,
    "type": "word",
    "start": 32,
    "end": 35,
    "value": "the"
  },
  {
    "time": 2292,
    "type": "viseme",
    "value": "T"
  },
  {
    "time": 2317,
    "type": "viseme",
    "value": "@"
  },
  {
    "time": 2417,
    "type": "word",
    "start": 36,
    "end": 38,
    "value": "Q4"
  },
  {
    "time": 2417,
    "type": "viseme",
    "value": "k"
  },
  {
    "time": 2442,
    "type": "viseme",
    "value": "i"
  },
  {
    "time": 2530,
    "type": "viseme",
    "value": "u"
  },
  {
    "time": 2692,
    "type": "viseme",
    "value": "f"
  },
  {
    "time": 2817,
    "type": "viseme",
    "value": "O"
  },
  {
    "time": 2842,
    "type": "viseme",
    "value": "r"
  },
  {
    "time": 2942,
    "type": "word",
    "start": 39,
    "end": 49,
    "value": "highlights"
  },
  {
    "time": 2942,
    "type": "viseme",
    "value": "k"
  },
  {
    "time": 3055,
    "type": "viseme",
    "value": "a"
  },
  {
    "time": 3192,
    "type": "viseme",
    "value": "t"
  },
  {
    "time": 3255,
    "type": "viseme",
    "value": "a"
  },
  {
    "time": 3317,
    "type": "viseme",
    "value": "t"
  },
  {
    "time": 3442,
    "type": "viseme",
    "value": "s"
  },
  {
    "time": 3467,
    "type": "word",
    "start": 50,
    "end": 53,
    "value": "and"
  },
  {
    "time": 3467,
    "type": "viseme",
    "value": "@"
  },
  {
    "time": 3505,
    "type": "viseme",
    "value": "t"
  },
  {
    "time": 3542,
    "type": "viseme",
    "value": "t"
  },
  {
    "time": 3567,
    "type": "word",
    "start": 54,
    "end": 55,
    "value": "a"
  },
  {
    "time": 3567,
    "type": "viseme",
    "value": "@"
  },
  {
    "time": 3655,
    "type": "word",
    "start": 56,
    "end": 59,
    "value": "few"
  },
  {
    "time": 3655,
    "type": "viseme",
    "value": "f"
  },
  {
    "time": 3767,
    "type": "viseme",
    "value": "i"
  },
  {
    "time": 3842,
    "type": "viseme",
    "value": "u"
  },
  {
    "time": 4017,
    "type": "word",
    "start": 60,
    "end": 66,
    "value": "slides"
  },
  {
    "time": 4017,
    "type": "viseme",
    "value": "s"
  },
  {
    "time": 4067,
    "type": "viseme",
    "value": "t"
  },
  {
    "time": 4167,
    "type": "viseme",
    "value": "a"
  },
  {
    "time": 4267,
    "type": "viseme",
    "value": "t"
  },
  {
    "time": 4330,
    "type": "viseme",
    "value": "s"
  },
  {
    "time": 4380,
    "type": "word",
    "start": 67,
    "end": 69,
    "value": "on"
  },
  {
    "time": 4380,
    "type": "viseme",
    "value": "a"
  },
  {
    "time": 4442,
    "type": "viseme",
    "value": "t"
  },
  {
    "time": 4567,
    "type": "word",
    "start": 70,
    "end": 75,
    "value": "early"
  },
  {
    "time": 4567,
    "type": "viseme",
    "value": "E"
  },
  {
    "time": 4692,
    "type": "viseme",
    "value": "t"
  },
  {
    "time": 4755,
    "type": "viseme",
    "value": "i"
  },
  {
    "time": 4867,
    "type": "word",
    "start": 76,
    "end": 78,
    "value": "Q1"
  },
  {
    "time": 4867,
    "type": "viseme",
    "value": "k"
  },
  {
    "time": 4880,
    "type": "viseme",
    "value": "i"
  },
  {
    "time": 4967,
    "type": "viseme",
    "value": "u"
  },
  {
    "time": 5067,
    "type": "viseme",
    "value": "u"
  },
  {
    "time": 5117,
    "type": "viseme",
    "value": "E"
  },
  {
    "time": 5192,
    "type": "viseme",
    "value": "t"
  },
  {
    "time": 5267,
    "type": "word",
    "start": 79,
    "end": 85,
    "value": "trends"
  },
  {
    "time": 5267,
    "type": "viseme",
    "value": "t"
  },
  {
    "time": 5330,
    "type": "viseme",
    "value": "r"
  },
  {
    "time": 5380,
    "type": "viseme",
    "value": "E"
  },
  {
    "time": 5505,
    "type": "viseme",
    "value": "t"
  },
  {
    "time": 5567,
    "type": "viseme",
    "value": "t"
  },
  {
    "time": 5717,
    "type": "viseme",
    "value": "s"
  },
  {
    "time": 5805,
    "type": "viseme",
    "value": "sil"
  },
  {
    "time": 6197,
    "type": "sentence",
    "start": 87,
    "end": 107,
    "value": "Shouldn't take long."
  },
  {
    "time": 6397,
    "type": "word",
    "start": 87,
    "end": 96,
    "value": "Shouldn't"
  },
  {
    "time": 6397,
    "type": "viseme",
    "value": "S"
  },
  {
    "time": 6435,
    "type": "viseme",
    "value": "u"
  },
  {
    "time": 6510,
    "type": "viseme",
    "value": "t"
  },
  {
    "time": 6572,
    "type": "viseme",
    "value": "t"
  },
  {
    "time": 6585,
    "type": "viseme",
    "value": "t"
  },
  {
    "time": 6697,
    "type": "word",
    "start": 97,
    "end": 101,
    "value": "take"
  },
  {
    "time": 6697,
    "type": "viseme",
    "value": "t"
  },
  {
    "time": 6760,
    "type": "viseme",
    "value": "e"
  },
  {
    "time": 6822,
    "type": "viseme",
    "value": "k"
  },
  {
    "time": 6947,
    "type": "word",
    "start": 102,
    "end": 106,
    "value": "long"
  },
  {
    "time": 6947,
    "type": "viseme",
    "value": "t"
  },
  {
    "time": 7035,
    "type": "viseme",
    "value": "a"
  },
  {
    "time": 7197,
    "type": "viseme",
    "value": "k"
  },
  {
    "time": 7285,
    "type": "viseme",
    "value": "sil"
  }
]